lightgbm_tools/__init__.py
lightgbm_tools/metrics.py
lightgbm_tools-0.0.2.dist-info/LICENSE
lightgbm_tools-0.0.2.dist-info/METADATA
lightgbm_tools-0.0.2.dist-info/WHEEL
lightgbm_tools-0.0.2.dist-info/top_level.txt
lightgbm_tools-0.0.2.dist-info/RECORD
